mongo_dash/__init__.py
mongo_dash/cli.py
mongo_dash/config.py
mongo_dash/database.py
mongo_dash/schemas.py
mongo_dash/server.py
mongo_dash/public/css/main.css
mongo_dash/public/css/tailwind.css
mongo_dash/public/js/modules/main.js
mongo_dash/routers/__init__.py
mongo_dash/routers/api.py
mongo_dash/routers/frontend.py
mongo_dash/templates/base.html
mongo_dash/templates/general/home.html
tests/__init__.py
tests/test_data.py
mongo_dash-0.1.6.dist-info/METADATA
mongo_dash-0.1.6.dist-info/WHEEL
mongo_dash-0.1.6.dist-info/entry_points.txt
mongo_dash-0.1.6.dist-info/top_level.txt
mongo_dash-0.1.6.dist-info/RECORD
