Metadata-Version: 2.1
Name: mongo-dash
Version: 0.1.6
Summary: Visualisation platform for MongoDB
Home-page: https://www.github.com/ismailuddin/mongo-dash
Author: Ismail Uddin
License: MIT license
Platform: UNKNOWN
Classifier: Development Status :: 2 - Pre-Alpha
Classifier: Intended Audience :: Developers
Classifier: License :: OSI Approved :: MIT License
Classifier: Natural Language :: English
Classifier: Programming Language :: Python :: 3
Classifier: Programming Language :: Python :: 3.6
Requires-Dist: fastapi
Requires-Dist: aiofiles
Requires-Dist: jinja2
Requires-Dist: uvicorn
Requires-Dist: motor
Requires-Dist: typer
Requires-Dist: async-exit-stack
Requires-Dist: async-generator
